healthchain/__init__.py
healthchain/cli.py
healthchain/config/__init__.py
healthchain/config/base.py
healthchain/config/validators.py
healthchain/configs/defaults.yaml
healthchain/configs/environments/development.yaml
healthchain/configs/environments/production.yaml
healthchain/configs/environments/testing.yaml
healthchain/configs/features/sepsis_vitals.yaml
healthchain/configs/interop/cda/document/ccd.yaml
healthchain/configs/interop/cda/sections/medications.yaml
healthchain/configs/interop/cda/sections/notes.yaml
healthchain/configs/interop/cda/sections/problems.yaml
healthchain/configs/mappings/README.md
healthchain/configs/mappings/cda_default/README.md
healthchain/configs/mappings/cda_default/severity_codes.yaml
healthchain/configs/mappings/cda_default/status_codes.yaml
healthchain/configs/mappings/cda_default/systems.yaml
healthchain/configs/templates/cda_fhir/condition.liquid
healthchain/configs/templates/cda_fhir/document_reference.liquid
healthchain/configs/templates/cda_fhir/medication_statement.liquid
healthchain/configs/templates/fhir_cda/document.liquid
healthchain/configs/templates/fhir_cda/medication_entry.liquid
healthchain/configs/templates/fhir_cda/note_entry.liquid
healthchain/configs/templates/fhir_cda/problem_entry.liquid
healthchain/configs/templates/fhir_cda/section.liquid
healthchain/fhir/__init__.py
healthchain/fhir/bundlehelpers.py
healthchain/fhir/dataframe.py
healthchain/fhir/elementhelpers.py
healthchain/fhir/readers.py
healthchain/fhir/resourcehelpers.py
healthchain/fhir/utilities.py
healthchain/fhir/version.py
healthchain/gateway/README.md
healthchain/gateway/__init__.py
healthchain/gateway/base.py
healthchain/gateway/api/__init__.py
healthchain/gateway/api/app.py
healthchain/gateway/api/dependencies.py
healthchain/gateway/api/protocols.py
healthchain/gateway/cds/__init__.py
healthchain/gateway/cds/events.py
healthchain/gateway/clients/__init__.py
healthchain/gateway/clients/auth.py
healthchain/gateway/clients/pool.py
healthchain-0.13.1.dist-info/METADATA
healthchain-0.13.1.dist-info/WHEEL
healthchain-0.13.1.dist-info/entry_points.txt
healthchain-0.13.1.dist-info/licenses/LICENSE
healthchain-0.13.1.dist-info/RECORD
