Metadata-Version: 2.4
Name: healthchain
Version: 0.13.1
Summary: Open source framework for productionizing healthcare AI
Project-URL: Homepage, https://dotimplement.github.io/HealthChain/
Project-URL: Repository, https://github.com/dotimplement/HealthChain
Author-email: Jennifer Jiang-Kells <jenniferjiangkells@gmail.com>, Adam Kells <adamjkells93@gmail.com>
License: Apache-2.0
License-File: LICENSE
Keywords: ai,ehr,fhir,healthcare,llm,mlops,nlp
Classifier: Development Status :: 3 - Alpha
Classifier: Intended Audience :: Developers
Classifier: Intended Audience :: Healthcare Industry
Classifier: Intended Audience :: Information Technology
Classifier: Intended Audience :: Science/Research
Classifier: Programming Language :: Python :: 3
Classifier: Topic :: Scientific/Engineering :: Artificial Intelligence
Requires-Python: <3.14,>=3.10
Requires-Dist: colorama<0.5,>=0.4.6
Requires-Dist: eval-type-backport<0.2,>=0.1.0
Requires-Dist: faker<26,>=25.1.0
Requires-Dist: fastapi-events<0.13,>=0.12.2
Requires-Dist: fastapi<0.128,>=0.115.3
Requires-Dist: fhir-resources<9,>=8.0.0
Requires-Dist: httpx<0.28,>=0.27.0
Requires-Dist: jinja2<4,>=3.1.3
Requires-Dist: jwt<2,>=1.3.1
Requires-Dist: lxml<6,>=5.2.2
Requires-Dist: numpy<2.4.0,>=1.26.0
Requires-Dist: pandas<3.0.0,>=1.0.0
Requires-Dist: pydantic<2.11.0,>=2.0.0
Requires-Dist: python-liquid<2,>=1.13.0
Requires-Dist: pyyaml<7,>=6.0.3
Requires-Dist: regex!=2019.12.17
Requires-Dist: spacy<4.0.0,>=3.0.0
Requires-Dist: starlette<0.50.0,>=0.40.0
Requires-Dist: termcolor<3,>=2.4.0
Requires-Dist: uvicorn<0.25,>=0.24.0
Requires-Dist: xmltodict<0.14,>=0.13.0
